<?xml version="1.0" encoding="utf-8"?>
<!DOCTYPE hibernate-mapping PUBLIC "-//Hibernate/Hibernate Mapping DTD 3.0//EN"
"http://hibernate.sourceforge.net/hibernate-mapping-3.0.dtd">
<!-- 
    Mapping file autogenerated by MyEclipse Persistence Tools
-->
<hibernate-mapping>
    <class name="com.tangotab.dao.pojo.DealDescription" table="deal_description">
        <id name="descriptionId" type="java.lang.Integer">
            <column name="DEAL_DESC_ID" />
            <generator class="identity" />
        </id>
        <property name="description" type="java.lang.String">
            <column name="DEAL_DESCRIPTION" length="50" not-null="true" />
        </property>
        <property name="isActive" type="java.lang.Short">
            <column name="IS_ACTIVE" length="2" not-null="true" />
        </property>
       <many-to-one name="dealName" class="com.tangotab.dao.pojo.DealName" fetch="select" lazy="proxy">
            <column name="DEAL_NAME_ID" not-null="true" />
        </many-to-one>
    </class>
</hibernate-mapping>
